README.md
pyproject.toml
setup.cfg
setup.py
src/RoboMachine.egg-info/PKG-INFO
src/RoboMachine.egg-info/SOURCES.txt
src/RoboMachine.egg-info/dependency_links.txt
src/RoboMachine.egg-info/entry_points.txt
src/RoboMachine.egg-info/requires.txt
src/RoboMachine.egg-info/top_level.txt
src/robomachine/__init__.py
src/robomachine/allpairsstrategy.py
src/robomachine/generator.py
src/robomachine/model.py
src/robomachine/parsing.py
src/robomachine/rules.py
src/robomachine/runner.py
src/robomachine/strategies.py