Metadata-Version: 2.1
Name: RoboMachine
Version: 0.10.0
Summary: Test data generator for Robot Framework
Home-page: https://github.com/mkorpela/RoboMachine
Download-URL: https://pypi.org/project/RoboMachine/
Author: Mikko Korpela
Author-email: mikko.korpela@gmail.com
License: Apache License, Version 2.0
Project-URL: Source, https://github.com/mkorpela/RoboMachine
Classifier: Intended Audience :: Developers
Classifier: Natural Language :: English
Classifier: Programming Language :: Python :: 3
Classifier: Topic :: Software Development :: Testing
Classifier: License :: OSI Approved :: Apache Software License
Classifier: Framework :: Robot Framework
Requires-Python: >=3.6
